setup.py
django_qrlink.egg-info/PKG-INFO
django_qrlink.egg-info/SOURCES.txt
django_qrlink.egg-info/dependency_links.txt
django_qrlink.egg-info/top_level.txt
qrlink/__init__.py
qrlink/decorators.py
qrlink/middleware.py