Metadata-Version: 1.0
Name: django-qrlink
Version: 0.1.0
Summary: Django middleware/decorator to insert a QR Code image link
Home-page: http://github.com/jaymzcd/django-qrlink/
Author: Jaymz Campbell
Author-email: jaymz@jaymz.eu
License: UNKNOWN
Platform: UNKNOWN
